Metadata-Version: 2.1
Name: flask-logfile
Version: 0.0.2
Summary: 一个高可用的Flask日志文件插件
Home-page: https://github.com/WALL-1/flask-logfile.git
Author: wall-1
License: UNKNOWN
Platform: UNKNOWN
